LICENSE
MANIFEST.in
README.md
requirements.txt
setup.cfg
setup.py
tests/__init__.py
tests/conftest.py
tests/filepaths.py
tests/test_all.py
tests/test_approx.py
tests/test_col_select.py
tests/test_dbs.py
tests/test_nested.py
tests/test_ordering.py
tests/test_partitions.py
tests/test_transforms.py
user_query_optimizer/__init__.py
user_query_optimizer/athena_optimizer.py
user_query_optimizer/filepaths.py
user_query_optimizer/optimizer.py
user_query_optimizer/presto_optimizer.py
user_query_optimizer/spark_optimizer.py
user_query_optimizer.egg-info/PKG-INFO
user_query_optimizer.egg-info/SOURCES.txt
user_query_optimizer.egg-info/dependency_links.txt
user_query_optimizer.egg-info/requires.txt
user_query_optimizer.egg-info/top_level.txt
user_query_optimizer/optimizations/__init__.py
user_query_optimizer/optimizations/approximates.py
user_query_optimizer/optimizations/column_selection.py
user_query_optimizer/optimizations/filtering_transforms.py
user_query_optimizer/optimizations/nested_subqueries.py
user_query_optimizer/optimizations/parquet_ordering.py
user_query_optimizer/optimizations/partitions.py