Metadata-Version: 1.0
Name: user-query-optimizer
Version: 0.1.6
Summary: SQL query optimization hints
Home-page: https://github.com/mozilla/user-query-optimizer
Author: Swathi Iyer
Author-email: swathii@stanford.edu
License: LICENSE.txt
Platform: UNKNOWN
